pymatic/__init__.py
pymatic/main.py
pymatic-0.2.0.dist-info/METADATA
pymatic-0.2.0.dist-info/WHEEL
pymatic-0.2.0.dist-info/entry_points.txt
pymatic-0.2.0.dist-info/top_level.txt
pymatic-0.2.0.dist-info/RECORD
